[
  {
    "rule_id": "high_sugar_per_100",
    "score_dimension": "sugar",
    "trigger_type": "data_threshold",
    "trigger_conditions": { "path": "nutrition_per_100.sugar_g", "gte": 10 },
    "impact_direction": "negative",
    "impact_weight": 100,
    "message": {
      "el": "Η υψηλή περιεκτικότητα σε ζάχαρη επιβαρύνει την αξιολόγηση.",
      "en": "High sugar weighs negatively on the assessment.",
      "de": "Ein hoher Zuckergehalt wirkt sich negativ auf die Bewertung aus.",
      "fr": "Une teneur élevée en sucre pèse négativement sur l’évaluation."
    }
  },
  {
    "rule_id": "high_sugar_per_serving",
    "score_dimension": "sugar",
    "trigger_type": "data_threshold",
    "trigger_conditions": { "path": "who_impact.sugar.percent_of_ideal_25g", "gte": 50 },
    "impact_direction": "negative",
    "impact_weight": 95,
    "message": {
      "el": "Η ζάχαρη ανά μερίδα καλύπτει μεγάλο μέρος του ημερήσιου ιδανικού ορίου.",
      "en": "Sugar per serving covers a large share of the ideal daily limit.",
      "de": "Der Zucker pro Portion deckt einen großen Teil des idealen Tageslimits ab.",
      "fr": "Le sucre par portion couvre une grande part de la limite idéale quotidienne."
    }
  },
  {
    "rule_id": "multiple_sweeteners",
    "score_dimension": "sweeteners",
    "trigger_type": "marker_min",
    "trigger_conditions": { "marker": "sweeteners", "min": 2 },
    "impact_direction": "negative",
    "impact_weight": 88,
    "message": {
      "el": "Η παρουσία πολλών γλυκαντικών μειώνει τη συνολική αξιολόγηση.",
      "en": "Multiple sweeteners reduce the overall assessment.",
      "de": "Mehrere Süßstoffe verringern die Gesamtbewertung.",
      "fr": "La présence de plusieurs édulcorants réduit l’évaluation globale."
    }
  },
  {
    "rule_id": "high_additive_load",
    "score_dimension": "additives",
    "trigger_type": "e_number_count_min",
    "trigger_conditions": { "min": 3 },
    "impact_direction": "negative",
    "impact_weight": 84,
    "message": {
      "el": "Η παρουσία πολλών προσθέτων επιβαρύνει την αξιολόγηση.",
      "en": "The presence of multiple additives weighs negatively on the assessment.",
      "de": "Das Vorhandensein mehrerer Zusatzstoffe wirkt sich negativ auf die Bewertung aus.",
      "fr": "La présence de plusieurs additifs pèse négativement sur l’évaluation."
    }
  },
  {
    "rule_id": "highly_processed_pattern",
    "score_dimension": "processing",
    "trigger_type": "processing_label_any",
    "trigger_terms": ["Highly processed"],
    "impact_direction": "negative",
    "impact_weight": 82,
    "message": {
      "el": "Η σύνθεση του προϊόντος είναι αρκετά επεξεργασμένη.",
      "en": "The product formulation is fairly processed.",
      "de": "Die Zusammensetzung des Produkts ist relativ stark verarbeitet.",
      "fr": "La formulation du produit reste assez transformée."
    }
  },
  {
    "rule_id": "colorants_present",
    "score_dimension": "colorants",
    "trigger_type": "marker_min",
    "trigger_conditions": { "marker": "colorants", "min": 1 },
    "impact_direction": "negative",
    "impact_weight": 70,
    "message": {
      "el": "Η παρουσία χρωστικών αυξάνει την πολυπλοκότητα της σύνθεσης.",
      "en": "The presence of colourants increases formulation complexity.",
      "de": "Das Vorhandensein von Farbstoffen erhöht die Komplexität der Zusammensetzung.",
      "fr": "La présence de colorants augmente la complexité de la composition."
    }
  },
  {
    "rule_id": "preservatives_present",
    "score_dimension": "preservatives",
    "trigger_type": "marker_min",
    "trigger_conditions": { "marker": "preservatives", "min": 1 },
    "impact_direction": "negative",
    "impact_weight": 68,
    "message": {
      "el": "Η παρουσία συντηρητικών επιβαρύνει τη συνολική εικόνα.",
      "en": "The presence of preservatives weighs negatively on the overall picture.",
      "de": "Das Vorhandensein von Konservierungsstoffen wirkt sich negativ auf das Gesamtbild aus.",
      "fr": "La présence de conservateurs pèse négativement sur l’ensemble."
    }
  },
  {
    "rule_id": "flavourings_present",
    "score_dimension": "flavourings",
    "trigger_type": "marker_min",
    "trigger_conditions": { "marker": "flavourings", "min": 1 },
    "impact_direction": "negative",
    "impact_weight": 60,
    "message": {
      "el": "Η παρουσία αρωμάτων δείχνει πιο σύνθετη σύνθεση.",
      "en": "The presence of flavourings suggests a more complex formulation.",
      "de": "Das Vorhandensein von Aromen weist auf eine komplexere Zusammensetzung hin.",
      "fr": "La présence d’arômes indique une composition plus complexe."
    }
  },
  {
    "rule_id": "syrup_or_simple_sugar_pattern",
    "score_dimension": "sugar",
    "trigger_type": "canonical_any",
    "trigger_terms": ["glucose syrup", "glucose-fructose syrup", "fructose-glucose syrup", "invert sugar syrup", "corn syrup", "sucrose", "glucose", "fructose"],
    "impact_direction": "negative",
    "impact_weight": 64,
    "message": {
      "el": "Σιρόπια ή απλά σάκχαρα επιβαρύνουν την αξιολόγηση.",
      "en": "Syrups or simple sugars weigh negatively on the assessment.",
      "de": "Sirupe oder einfache Zucker wirken sich negativ auf die Bewertung aus.",
      "fr": "Les sirops ou sucres simples pèsent négativement sur l’évaluation."
    }
  },
  {
    "rule_id": "salt_indicator",
    "score_dimension": "salt",
    "trigger_type": "data_threshold",
    "trigger_conditions": { "path": "nutrition_per_100.salt_g", "gte": 1 },
    "impact_direction": "negative",
    "impact_weight": 62,
    "message": {
      "el": "Η σχετικά υψηλή περιεκτικότητα σε αλάτι επιβαρύνει την εικόνα του προϊόντος.",
      "en": "Relatively high salt weighs negatively on the product profile.",
      "de": "Ein relativ hoher Salzgehalt wirkt sich negativ auf das Produktprofil aus.",
      "fr": "Une teneur en sel relativement élevée pèse négativement sur le profil du produit."
    }
  },
  {
    "rule_id": "simple_ingredient_profile",
    "score_dimension": "simplicity",
    "trigger_type": "all",
    "trigger_conditions": {
      "conditions": [
        { "trigger_type": "ingredient_count_lte", "trigger_conditions": { "max": 6 } },
        { "trigger_type": "e_number_count_max", "trigger_conditions": { "max": 1 } },
        { "trigger_type": "marker_max", "trigger_conditions": { "marker": "colorants", "max": 0 } },
        { "trigger_type": "marker_max", "trigger_conditions": { "marker": "preservatives", "max": 0 } },
        { "trigger_type": "marker_max", "trigger_conditions": { "marker": "sweeteners", "max": 0 } }
      ]
    },
    "impact_direction": "positive",
    "impact_weight": 90,
    "message": {
      "el": "Η απλή σύνθεση του προϊόντος λειτουργεί θετικά.",
      "en": "The simple ingredient profile helps the assessment.",
      "de": "Die einfache Zusammensetzung des Produkts wirkt sich positiv aus.",
      "fr": "La composition simple du produit aide l’évaluation."
    }
  },
  {
    "rule_id": "minimally_processed_pattern",
    "score_dimension": "processing",
    "trigger_type": "processing_label_any",
    "trigger_terms": ["Minimally processed"],
    "impact_direction": "positive",
    "impact_weight": 86,
    "message": {
      "el": "Η σχετικά χαμηλή επεξεργασία υποστηρίζει καλύτερη αξιολόγηση.",
      "en": "The relatively low processing level supports a better assessment.",
      "de": "Der relativ niedrige Verarbeitungsgrad unterstützt eine bessere Bewertung.",
      "fr": "Le niveau de transformation relativement faible soutient une meilleure évaluation."
    }
  },
  {
    "rule_id": "fortified_vitamins_minerals",
    "score_dimension": "fortification",
    "trigger_type": "canonical_any",
    "trigger_terms": ["vitamins", "vitamin c", "vitamin b6", "vitamin b12", "niacin", "riboflavin", "thiamine", "biotin", "calcium", "magnesium", "potassium"],
    "impact_direction": "neutral",
    "impact_weight": 55,
    "message": {
      "el": "Περιέχει εμπλουτισμένες βιταμίνες ή μέταλλα.",
      "en": "Contains added vitamins or minerals.",
      "de": "Enthält zugesetzte Vitamine oder Mineralstoffe.",
      "fr": "Contient des vitamines ou minéraux ajoutés."
    }
  },
  {
    "rule_id": "caffeine_present",
    "score_dimension": "caffeine",
    "trigger_type": "marker_min",
    "trigger_conditions": { "marker": "caffeine", "min": 1 },
    "impact_direction": "neutral",
    "impact_weight": 58,
    "message": {
      "el": "Η παρουσία καφεΐνης καταγράφεται ως αξιοσημείωτο στοιχείο.",
      "en": "Caffeine is recorded as a notable signal.",
      "de": "Das Vorhandensein von Koffein wird als auffälliges Signal erfasst.",
      "fr": "La présence de caféine est enregistrée comme un signal notable."
    }
  },
  {
    "rule_id": "carbonated_beverage_pattern",
    "score_dimension": "carbonation",
    "trigger_type": "canonical_any",
    "trigger_terms": ["carbonated water", "carbon dioxide"],
    "impact_direction": "neutral",
    "impact_weight": 50,
    "message": {
      "el": "Το προϊόν είναι ανθρακούχο.",
      "en": "The product is carbonated.",
      "de": "Das Produkt ist kohlensäurehaltig.",
      "fr": "Le produit est gazeux."
    }
  },
  {
    "rule_id": "acidifier_pattern",
    "score_dimension": "acidifier",
    "trigger_type": "canonical_any",
    "trigger_terms": ["acidifier", "citric acid", "phosphoric acid", "malic acid", "lactic acid", "sodium citrate"],
    "impact_direction": "neutral",
    "impact_weight": 46,
    "message": {
      "el": "Εντοπίστηκαν συστατικά που ρυθμίζουν την οξύτητα.",
      "en": "Ingredients used to control acidity were detected.",
      "de": "Zutaten zur Regulierung der Säure wurden erkannt.",
      "fr": "Des ingrédients utilisés pour ajuster l’acidité ont été détectés."
    }
  },
  {
    "rule_id": "sweetener_heavy_zero_beverage",
    "score_dimension": "sweetener_complexity",
    "trigger_type": "all",
    "trigger_conditions": {
      "conditions": [
        { "trigger_type": "marker_min", "trigger_conditions": { "marker": "sweeteners", "min": 2 } },
        { "trigger_type": "data_threshold", "trigger_conditions": { "path": "nutrition_per_100.sugar_g", "lte": 1.5 } },
        { "trigger_type": "canonical_any", "trigger_terms": ["carbonated water", "carbon dioxide"] },
        { "trigger_type": "any", "trigger_conditions": { "conditions": [
          { "trigger_type": "e_number_count_min", "trigger_conditions": { "min": 3 } },
          { "trigger_type": "marker_min", "trigger_conditions": { "marker": "flavourings", "min": 1 } },
          { "trigger_type": "marker_min", "trigger_conditions": { "marker": "colorants", "min": 1 } },
          { "trigger_type": "processing_label_any", "trigger_terms": ["Highly processed"] }
        ]}}
      ]
    },
    "impact_direction": "negative",
    "impact_weight": 98,
    "message": {
      "el": "Η απουσία ζάχαρης δεν αρκεί από μόνη της για πολύ υψηλή τελική αξιολόγηση όταν η σύνθεση παραμένει σύνθετη.",
      "en": "The absence of sugar alone is not enough for a very high final assessment when the formulation remains complex.",
      "de": "Das Fehlen von Zucker allein reicht nicht für eine sehr hohe Endbewertung, wenn die Zusammensetzung komplex bleibt.",
      "fr": "L’absence de sucre ne suffit pas à elle seule pour une très bonne évaluation finale lorsque la formulation reste complexe."
    }
  },
  {
    "rule_id": "non_sugar_sweetener_presence",
    "score_dimension": "sweeteners",
    "trigger_type": "all",
    "trigger_conditions": {
      "conditions": [
        { "trigger_type": "marker_min", "trigger_conditions": { "marker": "sweeteners", "min": 1 } },
        { "trigger_type": "data_threshold", "trigger_conditions": { "path": "nutrition_per_100.sugar_g", "lte": 1.5 } }
      ]
    },
    "impact_direction": "negative",
    "impact_weight": 78,
    "message": {
      "el": "Παρότι είναι χωρίς ζάχαρη, η σύνθεση παραμένει αρκετά σύνθετη.",
      "en": "Although it is sugar-free, the formulation remains fairly complex.",
      "de": "Obwohl das Produkt zuckerfrei ist, bleibt die Zusammensetzung relativ komplex.",
      "fr": "Même sans sucre, la formulation reste assez complexe."
    }
  },
  {
    "rule_id": "simple_reduced_fat_dairy",
    "score_dimension": "reduced_fat_dairy_simple",
    "trigger_type": "all",
    "trigger_conditions": {
      "conditions": [
        { "trigger_type": "product_text_any", "trigger_terms": ["light", "lite", "low fat", "low-fat", "reduced fat", "reduced-fat", "0%", "fettreduziert", "allégé", "χαμηλά λιπαρά", "μειωμένων λιπαρών"] },
        { "trigger_type": "product_text_any", "trigger_terms": ["milk", "milch", "lait", "yogurt", "yoghurt", "yaourt", "cheese", "käse", "fromage", "γάλα", "γιαούρ", "τυρί"] },
        { "trigger_type": "marker_max", "trigger_conditions": { "marker": "sweeteners", "max": 0 } },
        { "trigger_type": "marker_max", "trigger_conditions": { "marker": "flavourings", "max": 0 } },
        { "trigger_type": "marker_max", "trigger_conditions": { "marker": "emulsifiers_stabilizers", "max": 0 } },
        { "trigger_type": "e_number_count_max", "trigger_conditions": { "max": 1 } },
        { "trigger_type": "ingredient_count_lte", "trigger_conditions": { "max": 6 } }
      ]
    },
    "impact_direction": "positive",
    "impact_weight": 76,
    "message": {
      "el": "Η απλή σύνθεση του light γαλακτοκομικού λειτουργεί θετικά.",
      "en": "The simple composition of this reduced-fat dairy product helps the assessment.",
      "de": "Die einfache Zusammensetzung dieses fettreduzierten Milchprodukts wirkt sich positiv aus.",
      "fr": "La composition simple de ce produit laitier allégé aide l’évaluation."
    }
  },
  {
    "rule_id": "reduced_fat_dairy_additive_heavy",
    "score_dimension": "flavored_light_dairy",
    "trigger_type": "all",
    "trigger_conditions": {
      "conditions": [
        { "trigger_type": "product_text_any", "trigger_terms": ["light", "lite", "low fat", "low-fat", "reduced fat", "reduced-fat", "0%", "fettreduziert", "allégé", "χαμηλά λιπαρά", "μειωμένων λιπαρών"] },
        { "trigger_type": "product_text_any", "trigger_terms": ["milk", "milch", "lait", "yogurt", "yoghurt", "yaourt", "cheese", "käse", "fromage", "γάλα", "γιαούρ", "τυρί"] },
        { "trigger_type": "any", "trigger_conditions": { "conditions": [
          { "trigger_type": "marker_min", "trigger_conditions": { "marker": "sweeteners", "min": 1 } },
          { "trigger_type": "marker_min", "trigger_conditions": { "marker": "flavourings", "min": 1 } },
          { "trigger_type": "marker_min", "trigger_conditions": { "marker": "emulsifiers_stabilizers", "min": 1 } },
          { "trigger_type": "e_number_count_min", "trigger_conditions": { "min": 2 } },
          { "trigger_type": "processing_label_any", "trigger_terms": ["Highly processed"] }
        ]}}
      ]
    },
    "impact_direction": "negative",
    "impact_weight": 74,
    "message": {
      "el": "Το προϊόν είναι μειωμένων λιπαρών, αλλά η σύνθεσή του παραμένει αρκετά επεξεργασμένη.",
      "en": "The product is reduced-fat, but its formulation remains fairly processed.",
      "de": "Das Produkt ist fettreduziert, bleibt aber in seiner Zusammensetzung relativ stark verarbeitet.",
      "fr": "Le produit est allégé, mais sa formulation reste assez transformée."
    }
  }
]
